{"name":"User membuka tulis jawaban","id":"user-on-landing-page;user-membuka-tulis-jawaban","testSteps":[{"number":1,"description":"Given user login with email ii@gmail.com and password 123 and user on landing page","duration":4440,"startTime":"2022-07-17T20:11:18.048905100+07:00[Asia/Jakarta]","screenshots":[{"screenshot":"2d16ea07decf7f1f13ad84179e2e34e557539afdd9e96bc737b7fa8f47eb7e74.png","timeStamp":1658063482489}],"result":"SUCCESS","precondition":false,"level":0,"children":[{"number":2,"description":"Open page","duration":3128,"startTime":"2022-07-17T20:11:18.070910700+07:00[Asia/Jakarta]","screenshots":[{"screenshot":"782dc78b0f08bbf214e0ae243b118e25f1cdfbefd79bca6adab077374681cf4e.png","timeStamp":1658063481199}],"result":"SUCCESS","precondition":false,"level":1},{"number":3,"description":"On landingpage","duration":535,"startTime":"2022-07-17T20:11:21.951019200+07:00[Asia/Jakarta]","screenshots":[{"screenshot":"7fcc1d736ce0a2dff0c345543d4048393d89958811b0ac74627e32d942033ffa.png","timeStamp":1658063482113},{"screenshot":"2d16ea07decf7f1f13ad84179e2e34e557539afdd9e96bc737b7fa8f47eb7e74.png","timeStamp":1658063482486}],"result":"SUCCESS","precondition":false,"level":1}]},{"number":4,"description":"When user klik \u0027tulis\u0027 button","duration":292,"startTime":"2022-07-17T20:11:22.489356600+07:00[Asia/Jakarta]","screenshots":[{"screenshot":"f3dfd4916734bf7e81bdec126d2b7c39b20e5b9eebc3d426bf00727e99ca512a.png","timeStamp":1658063482782}],"result":"SUCCESS","precondition":false,"level":0,"children":[{"number":5,"description":"Click tulis button","duration":289,"startTime":"2022-07-17T20:11:22.489356600+07:00[Asia/Jakarta]","screenshots":[{"screenshot":"f3dfd4916734bf7e81bdec126d2b7c39b20e5b9eebc3d426bf00727e99ca512a.png","timeStamp":1658063482779}],"result":"SUCCESS","precondition":false,"level":1}]},{"number":6,"description":"Then user sukses ke halaman tulis","duration":8,"startTime":"2022-07-17T20:11:22.783107700+07:00[Asia/Jakarta]","screenshots":[{"screenshot":"f3dfd4916734bf7e81bdec126d2b7c39b20e5b9eebc3d426bf00727e99ca512a.png","timeStamp":1658063482792}],"result":"SUCCESS","precondition":false,"level":0,"children":[{"number":7,"description":"Validate on tulis page","duration":3,"startTime":"2022-07-17T20:11:22.786112200+07:00[Asia/Jakarta]","screenshots":[{"screenshot":"f3dfd4916734bf7e81bdec126d2b7c39b20e5b9eebc3d426bf00727e99ca512a.png","timeStamp":1658063482789}],"result":"SUCCESS","precondition":false,"level":1}]}],"userStory":{"id":"user-on-landing-page","storyName":"User on landing page","path":"file:///C:/Users/LENOVO-PC/OneDrive%20-%20IT-PLN/Dokumen/apenim/Diskusiaza-QE/WEB%20DISKUSIAZA/src/test/resources/web/LandingPage.feature","type":"feature"},"featureTag":{"name":"Web/User on landing page","type":"feature","displayName":"Web/User on landing page"},"title":"User membuka tulis jawaban","description":"","startTime":"2022-07-17T20:11:18.041904200+07:00[Asia/Jakarta]","duration":4751,"projectKey":"","sessionId":"3934a6cb29574d2fa06f1a77b42b3c93","driver":"chrome","isManualTestingUpToDate":false,"manual":false,"testSource":"Cucumber","result":"SUCCESS"}