{"name":"User update data profile","id":"as-a-user-on-profil-page;user-update-data-profile","testSteps":[{"number":1,"description":"Given user put profile endpoints","duration":2,"startTime":"2022-07-03T22:26:43.135073300+07:00[Asia/Jakarta]","result":"PENDING","precondition":false,"level":0},{"number":2,"description":"When user input update body","duration":3,"startTime":"2022-07-03T22:26:43.137074900+07:00[Asia/Jakarta]","result":"IGNORED","precondition":false,"level":0},{"number":3,"description":"Then user get valid response code 200","duration":3,"startTime":"2022-07-03T22:26:43.141075900+07:00[Asia/Jakarta]","result":"IGNORED","precondition":false,"level":0},{"number":4,"description":"And user get update data profile","duration":3,"startTime":"2022-07-03T22:26:43.146075300+07:00[Asia/Jakarta]","result":"IGNORED","precondition":false,"level":0}],"userStory":{"id":"as-a-user-on-profil-page","storyName":"As a user on profil page","path":"file:///C:/Users/LENOVO-PC/OneDrive%20-%20IT-PLN/Dokumen/apenim/Diskusiaza-QE/REST%20API%20CAPSTONE/src/test/resources/api/Profile.feature","type":"feature"},"featureTag":{"name":"Api/As a user on profil page","type":"feature","displayName":"Api/As a user on profil page"},"title":"User update data profile","description":"","startTime":"2022-07-03T22:26:43.131072+07:00[Asia/Jakarta]","duration":19,"projectKey":"","annotatedResult":"PENDING","isManualTestingUpToDate":false,"manual":false,"testSource":"Cucumber","result":"PENDING"}